sigmaepsilon/solid/material/__init__.py
sigmaepsilon/solid/material/config.py
sigmaepsilon/solid/material/elasticitytensor.py
sigmaepsilon/solid/material/enums.py
sigmaepsilon/solid/material/evaluator.py
sigmaepsilon/solid/material/exceptions.py
sigmaepsilon/solid/material/failure/__init__.py
sigmaepsilon/solid/material/failure/abstract.py
sigmaepsilon/solid/material/failure/hmh.py
sigmaepsilon/solid/material/failure/hoffman.py
sigmaepsilon/solid/material/frame/__init__.py
sigmaepsilon/solid/material/frame/bernoulliframe.py
sigmaepsilon/solid/material/linearelasticmaterial.py
sigmaepsilon/solid/material/proto.py
sigmaepsilon/solid/material/straintensor.py
sigmaepsilon/solid/material/stresstensor.py
sigmaepsilon/solid/material/surface/__init__.py
sigmaepsilon/solid/material/surface/kirchhoffplate.py
sigmaepsilon/solid/material/surface/kirchhoffshell.py
sigmaepsilon/solid/material/surface/membrane.py
sigmaepsilon/solid/material/surface/mindlinplate.py
sigmaepsilon/solid/material/surface/mindlinshell.py
sigmaepsilon/solid/material/surface/surface.py
sigmaepsilon/solid/material/tensor2x3.py
sigmaepsilon/solid/material/testing.py
sigmaepsilon/solid/material/utils/__init__.py
sigmaepsilon/solid/material/utils/bernoulli.py
sigmaepsilon/solid/material/utils/hmh.py
sigmaepsilon/solid/material/utils/hoffman.py
sigmaepsilon/solid/material/utils/imap.py
sigmaepsilon/solid/material/utils/material.py
sigmaepsilon/solid/material/utils/mindlin.py
sigmaepsilon/solid/material/utils/postproc.py
sigmaepsilon/solid/material/utils/principal.py
sigmaepsilon/solid/material/utils/surface.py
sigmaepsilon/solid/material/utils/symbolic.py
sigmaepsilon/solid/material/utils/tr.py
sigmaepsilon/solid/material/utils/utils.py
sigmaepsilon/solid/material/warnings.py
sigmaepsilon_solid_material-1.0.2.dist-info/LICENSE
sigmaepsilon_solid_material-1.0.2.dist-info/METADATA
sigmaepsilon_solid_material-1.0.2.dist-info/WHEEL
sigmaepsilon_solid_material-1.0.2.dist-info/RECORD
