Metadata-Version: 2.1
Name: sigmaepsilon.solid.material
Version: 1.0.2
Summary: Material models for solid structures in Python.
Home-page: https://github.com/sigma-epsilon/sigmaepsilon.solid.material
License: MIT
Keywords: engineering,mechanics,solid mechanics,Python,numerical methods,material models,material properties,material testing,material characterization,material science
Author: Bence Balogh
Author-email: bencebalogh@sigmaepsilon.com
Maintainer: Bence Balogh
Maintainer-email: bencebalogh@sigmaepsilon.com
Requires-Python: >=3.10,<3.13
Classifier: Development Status :: 5 - Production/Stable
Classifier: License :: OSI Approved :: MIT License
Classifier: Operating System :: OS Independent
Classifier: Programming Language :: Python :: 3
Classifier: Programming Language :: Python :: 3.10
Classifier: Programming Language :: Python :: 3.11
Classifier: Programming Language :: Python :: 3.12
Classifier: Programming Language :: Python :: 3 :: Only
Requires-Dist: sigmaepsilon-mesh (>=3.0.2,<4.0.0)
Requires-Dist: xarray (>=2024.2.0,<2025.0.0)
Project-URL: Documentation, https://sigmaepsilonsolidmaterial.readthedocs.io/en/latest/?badge=latest
Project-URL: Repository, https://github.com/sigma-epsilon/sigmaepsilon.solid.material
